pycrowipmodule/__init__.py
pycrowipmodule/alarm_panel.py
pycrowipmodule/crow_base_client.py
pycrowipmodule/crow_defs.py
pycrowipmodule/status_state.py
pycrowipmodule-0.32.dist-info/LICENSE
pycrowipmodule-0.32.dist-info/METADATA
pycrowipmodule-0.32.dist-info/WHEEL
pycrowipmodule-0.32.dist-info/top_level.txt
pycrowipmodule-0.32.dist-info/RECORD
