Metadata-Version: 2.1
Name: pycrowipmodule
Version: 0.32
Summary: Library for Crow/AAP Alarm Ip Module
Home-page: https://github.com/febalci/pycrowipmodule
Author: febalci
Author-email: febalci@yahoo.com
License: MIT
Keywords: Crow/AAP Alarm Ip Module for Home Assistant
License-File: LICENSE
Requires-Dist: requests
